{
  "holidays": {
    "advent1": "1st Sunday of Advent",
    "advent2": "2nd Sunday of Advent",
    "advent3": "3rd Sunday of Advent",
    "advent4": "4th Sunday of Advent",
    "christmas": "Christmas - The Festival of the Nativity of Our Lord",
    "christmas+1": "1st Sunday after Christmas",
    "christmas+2": "2nd Sunday after Christmas",
    "epiphany": "Epiphany - The Festival of the Epiphany of Our Lord",
    "epiphany+1": "1st Sunday after Epiphany",
    "epiphany+2": "2nd Sunday after Epiphany",
    "epiphany+3": "3rd Sunday after Epiphany",
    "epiphany+4": "4th Sunday after Epiphany",
    "epiphany+5": "5th Sunday after Epiphany",
    "epiphany+6": "6th Sunday after Epiphany",
    "lent-3": "3rd last Sunday before Lent (Septuagesima)",
    "lent-2": "2nd last Sunday before Lent (Sexagesima)",
    "lent-1": "Last Sunday before Lent (Quinquagesima)",
    "lent1": "1st Sunday in Lent",
    "lent2": "2nd Sunday in Lent",
    "lent3": "3rd Sunday in Lent",
    "lent4": "4th Sunday in Lent",
    "lent5": "5th Sunday in Lent",
    "lent6": "6th Sunday in Lent",
    "lent7": "Last Sunday in Lent (Palm Sunday)",
    "holy_mo": "Monday of Holy Week",
    "holy_tu": "Tuesday of Holy Week",
    "holy_we": "Wednesday of Holy Week",
    "holy_th": "Maundy Thursday",
    "holy_fr": "Good Friday",
    "holy_sa": "Holy Saturday",
    "easter": "Easter - The Festival of the Resurrection of Our Lord",
    "easter_mo": "Easter Monday",
    "easter+1": "1st Sunday after Easter",
    "easter+2": "2nd Sunday after Easter",
    "easter+3": "3rd Sunday after Easter",
    "easter+4": "4th Sunday after Easter",
    "easter+5": "5th Sunday after Easter",
    "ascension": "Ascension - The Festival of the Ascension of Our Lord",
    "ascension+1": "6th Sunday after Easter (Sunday after Ascension)",
    "pentecost": "Pentecost - The Festival of the Coming of the Holy Spirit",
    "pentecost+1": "1st Sunday after Pentecost",
    "pentecost+2": "2nd Sunday after Pentecost",
    "trinity": "The Festival of the Holy Trinity",
    "trinity+1": "1st Sunday after Trinity",
    "trinity+2": "2nd Sunday after Trinity",
    "trinity+3": "3rd Sunday after Trinity",
    "trinity+4": "4th Sunday after Trinity",
    "trinity+5": "5th Sunday after Trinity",
    "trinity+6": "6th Sunday after Trinity",
    "trinity+7": "7th Sunday after Trinity",
    "trinity+8": "8th Sunday after Trinity",
    "trinity+9": "9th Sunday after Trinity",
    "trinity+10": "10th Sunday after Trinity",
    "trinity+11": "11th Sunday after Trinity",
    "trinity+12": "12th Sunday after Trinity",
    "trinity+13": "13th Sunday after Trinity",
    "trinity+14": "14th Sunday after Trinity",
    "trinity+15": "15th Sunday after Trinity",
    "trinity+16": "16th Sunday after Trinity",
    "trinity+17": "17th Sunday after Trinity",
    "trinity+18": "18th Sunday after Trinity",
    "trinity+19": "19th Sunday after Trinity",
    "trinity+20": "20th Sunday after Trinity",
    "trinity+21": "21st Sunday after Trinity",
    "trinity+22": "22nd Sunday after Trinity",
    "trinity+23": "23rd Sunday after Trinity",
    "judgment-1": "Sunday before Last Judgement Sunday",
    "judgment": "Last Judgement Sunday",
    "circumcision": "Feast of the Circumcision of Jesus",
    "temple": "Feast of the Entry of Jesus into the Temple",
    "annunciation": "Feast of the Annunciation",
    "tabor": "The Transfiguration of Jesus on Mt. Tabor (Buhe)",
    "last": "Last Sunday of the year",
    "newyear": "Ethiopian New Year",
    "mesqel": "Finding of the True Cross",
    "reformation": "Reformation Day",
    "martyrs": "Feast of the Martyrs"
  },
  "themes": {
    "advent1": "The Lord's coming to the temple",
    "advent2": "The coming of the Lord into his kingdom",
    "advent3": "Preparing the way",
    "advent4": "The coming of the Lord is near",
    "christmas": "The birth of our Lord",
    "christmas+1": "Living in peace as children of God",
    "christmas+2": "The Magi worship baby Jesus",
    "epiphany": "The Baptism of Jesus",
    "epiphany+1": "Preaching the Good News to the whole world",
    "epiphany+2": "Jesus sanctifies our life",
    "epiphany+3": "Jesus strengthens our faith",
    "epiphany+4": "Jesus helps in times of need",
    "epiphany+5": "Revealing the hidden glory of the kingdom of heaven",
    "epiphany+6": "God's work never ends",
    "lent-3": "God's grace",
    "lent-2": "God's word",
    "lent-1": "God's love",
    "lent1": "Fighting temptation",
    "lent2": "A strong foundation of faith",
    "lent3": "Fighting the forces of evil",
    "lent4": "The bread of life",
    "lent5": "Our mediator",
    "lent6": "The new life",
    "lent7": "The new covenant",
    "holy_mo": "The suffering Christ",
    "holy_tu": "The suffering Christ",
    "holy_we": "The suffering Christ",
    "holy_th": "The Lord's Supper",
    "holy_fr": "Jesus' crucifixion",
    "holy_sa": "Jesus' burial",
    "easter": "The Resurrection of Jesus",
    "easter_mo": "Meeting with the living Lord",
    "easter+1": "The heart of our salvation",
    "easter+2": "The Lord is our shepherd",
    "easter+3": "Longing for our heavenly home",
    "easter+4": "The path of holiness",
    "easter+5": "Prayer",
    "ascension": "Jesus ascends into heaven",
    "ascension+1": "The promised coming of the Holy Spirit",
    "pentecost": "The outpouring of the Holy Spirit",
    "pentecost+1": "The gifts of the Holy Spirit",
    "pentecost+2": "The fruit of the Spirit and the works of the flesh",
    "trinity": "Father, Son, and Holy Spirit",
    "trinity+1": "Choosing God or the world",
    "trinity+2": "Called to the Kingdom of God",
    "trinity+3": "The unity of the church",
    "trinity+4": "Righteousness and compassion",
    "trinity+5": "Living as a disciple to the end",
    "trinity+6": "Love",
    "trinity+7": "Standing firm against sin",
    "trinity+8": "Faithful and wise stewardship",
    "trinity+9": "Make the most of every opportunity",
    "trinity+10": "True and false righteousness",
    "trinity+11": "Listening and speaking",
    "trinity+12": "Loving our neighbor",
    "trinity+13": "Thanksgiving",
    "trinity+14": "Seeking the Kingdom of God",
    "trinity+15": "Taking care of creation",
    "trinity+16": "Spiritual freedom",
    "trinity+17": "Drawing close to the Lord",
    "trinity+18": "Victorious faith",
    "trinity+19": "Working hard and providing for the church and others",
    "trinity+20": "Forgiving each other",
    "trinity+21": "Obedience to God and leaders",
    "trinity+22": "Resurrection and eternal life",
    "trinity+23": "The end times",
    "judgment-1": "Waiting in anticipation",
    "judgment": "The last judgment",
    "circumcision": "The Name of Jesus",
    "temple": "Christ reveals God to us",
    "annunciation": "God's messenger",
    "tabor": "Jesus shows his glory",
    "last": "Day of Repentance",
    "newyear": "A new season",
    "mesqel": "The cross of Christ",
    "reformation": "Salvation through Christ and grace alone / Righteousness through faith alone / The Bible as the basis of faith alone",
    "martyrs": ""
  },
  "prayers": {
    "advent1": "Lord Jesus Christ! Come into the midst of your church and cleanse our hearts with your power. By your mercy free us from all the corruption of sin, so that we may receive you, our true King, with joy. Father, Son, Holy Spirit, one God who lives forever, hear our prayers. Amen.",
    "advent2": "Lord God, let us wait with thanksgiving for the coming of your Son, the Lord Jesus Christ. Awaken our hearts to prepare the way for him, and serve him with free will and a clear conscience. We ask you in the name of our Lord Jesus Christ, who lives and reigns with you and the Holy Spirit, one God now and forever. Amen.",
    "advent3": "O Lord our God, help us as we wait in faith for the coming of your Son Jesus Christ to this earth. Visit us your children and help us prepare our hearts for him. Strengthen us in grace by your Holy Spirit so that we will be truly ready for the coming of Jesus Christ our Lord. Amen.",
    "advent4": "Holy God our Father, we thank you for the joy you give us by the coming of your Son into this world. Help us by your Holy Spirit, for the sake of your holy name and your glory, to receive him with joy as our only Savior. Amen.",
    "christmas": "Almighty God, we thank you for sending your only Son Jesus Christ for our salvation and blessing. He is the light of your glory, the visible image of the invisible God. Help us by the power of the Holy Spirit to open our hearts to Him so that we may be cleansed of all sin and live with Him in heaven. Hear us in the name of your Son, Jesus Christ. Amen.",
    "christmas+1": "Holy God our Father, our Lord Jesus Christ humbled himself, taking on our human nature, and also showed us your power. Grant to us your children that we may live in peace without fear. Hear us in the name of your beloved Son, Jesus Christ, who lives and reigns forever with you and the Holy Spirit. Amen.",
    "christmas+2": "Almighty and eternal God, as you led the wise men by the star of your Son Jesus Christ, we ask you in his name to guide us, who believe and trust in you by the power of the Holy Spirit, to behold his glory forever in heaven. Amen.",
    "epiphany": "Almighty God, you are the one who gives strength to those who ask. Because our human efforts are powerless without you, help us by the power of your Holy Spirit, given through baptism, to walk as your children in this life now, and to inherit eternal life in the world to come. Hear the prayers of your children who pray in Jesus' name. Amen.",
    "epiphany+1": "O Lord our God, who created and sustains the world with your great power, you love your whole creation and desire that all people be saved and come to know the truth. In the name of our Lord Jesus Christ, who is the Savior of the world, we ask you to raise up servants of your kingdom to preach the gospel, both inside and outside our country, and to give listening ears and hearts of repentance to those who hear their message. Amen.",
    "epiphany+2": "Almighty God, because you are the ruler of heaven and earth, help us by the power of the Holy Spirit to live in praise of your name all our days, in the name of Jesus Christ your Son our Lord. Amen.",
    "epiphany+3": "Almighty and eternal God, daily increase your Holy Spirit and your grace so that we may trust more and more in the hope that you have given us. Awaken us and help us with your power so that we may live safely under your guiding hand. Hear us in the name of our Lord Jesus Christ. Amen.",
    "epiphany+4": "Almighty Heavenly Father, you know that, because of the weakness of our flesh, we cannot overcome all trials and tribulations. Therefore we ask you to strengthen our bodies and souls in times of trouble and hardship, so that we may triumph in the power of your Holy Spirit. Hear us in the name of our Lord Jesus Christ. Amen.",
    "epiphany+5": "God, heavenly father, be a refuge for those who believe in you and hope only in your grace. Protect your people with the power of your Holy Spirit so that they may live in your love; in the name of our Lord Jesus Christ. Amen.",
    "epiphany+6": "God, Heavenly Father, you are the Author and Finisher of all the good in our hearts. Help us by your Holy Spirit, in the name of your only Son, Jesus Christ, to grow in the love of Christ and in good deeds, knowing that we receive everything good from your grace alone. Amen.",
    "lent-3": "Dear God, when we were worthy of death for our sins, you redeemed us through your only Son Jesus Christ. Comfort us now with your Holy Spirit, and in your mercy save us. In the name of our Lord Jesus Christ. Amen.",
    "lent-2": "Lord, you know that we cannot understand your Word by our own strength or wisdom. We ask you in the name of Jesus Christ that your Holy Spirit, who is our teacher, will guide us in all truth and protect us from everything that prevents us from understanding your Word. Amen.",
    "lent-1": "Lord our God, you tell us that everything done without love is worthless. Pour out your love in our hearts by the power of the Holy Spirit, so that we may be cleansed from sin and live with you forever. In the name of Jesus Christ our Lord. Amen.",
    "lent1": "God, our Heavenly Father, you sent your only Son to be tried and tested in our trials and tribulations. Help us by your Holy Spirit to be his followers, and overcome our enemy with his power. In the name of Jesus Christ our Lord. Amen.",
    "lent2": "Most High God, Heavenly Father, you know that by ourselves we can do nothing good. Protect our bodies from all evil, and cleanse our souls from all wicked thoughts, and protect us throughout our earthly and spiritual lives, in the name of our Lord Jesus Christ. Amen.",
    "lent3": "Almighty God, we thank you for drawing us to yourself so that we can escape from the powers of darkness and always walk as children of light. In the name of your only Son Jesus Christ, we now ask you to keep us in your mighty power all the days of our lives. Amen.",
    "lent4": "Almighty God, it is your will to save us, who are sorely afflicted by sin. Make us hunger and thirst for your righteousness. Strengthen our hearts with the power of your Holy Spirit. In the name of our Lord Jesus Christ. Amen.",
    "lent5": "Almighty God, look upon your people, the church, for whom our Lord Jesus Christ suffered the pain of death on the cross. Give us your power to be faithful followers, and make us partakers of the salvation which he has prepared for us. In the name of your beloved Son, Jesus Christ, who lives and reigns forever with you and the Holy Spirit. Amen.",
    "lent6": "Almighty and eternal God, our Savior Jesus Christ was humbled to become man and die on the cross for us. In his mightly and exulted name, help us by your grace to be partakers of the joy of the resurrection with him. Amen.",
    "lent7": "Eternal God, when we remember the severity of our sins for which your Son, our Lord Jesus Christ suffered, we are brought again to repentance and faith. Thank you for blotting out our sins by his death and resurrection. In Jesus' name. Amen.",
    "holy_fr": "Our Holy Heavenly Father, you did not spare your only Son, but gave him up to die for us on the cross. In his name, we now ask you to send your Holy Spirit to dwell in our hearts. Lead us to trust only in your grace, and so obtain eternal life through the blood of your Son Jesus. Amen.",
    "easter": "Almighty and eternal God, you led your people out of the land of Egypt under the leadership of Moses and commanded them to eat the Passover every year. We ask now you to lead us out of our spiritual slavery to sin and make us partakers of the true Passover Lamb. On this day, our Lord Jesus Christ defeated death by His resurrection from the dead and opened the way for us to eternal life. Because he now lives, he will reign with you and the Holy Spirit forever. Glory and praise be to him. Amen.",
    "easter_mo": "God, our heavenly Father, we thank you that your Son Jesus Christ rose from the dead and appeared to his disciples. Reveal him to us in your living Word. Help us by the power of your Holy Spirit to be witnesses of his resurrection until the end. In the name of our Lord Jesus Christ. Amen.",
    "easter+1": "Almighty and eternal God, we thank you with all our heart for bringing us to the celebration of the feast of the Resurrection. Give us faith in the forgiving word of the cross. Cleanse us from sin and give us power to walk in newness of life. In the name of your only Son, Jesus Christ, who lives and reigns forever with you and the Holy Spirit. Amen.",
    "easter+2": "Almighty God, we thank you for saving our sinful world through the resurrection of your Son Jesus Christ from the dead. In his name, help us by the power of your Holy Spirit so that we may always hold fast to you in faith and be saved from eternal death, to become partakers of eternal joy with all believers. Amen.",
    "easter+3": "God our Heavenly Father, you are the one who rules the hearts of all believers and gives them unity with your Holy Spirit. Help all of us who are walking in this world, which is passing away, to rest our hearts in Jesus and so set our minds on the world that will not pass away. In the name of our Lord Jesus Christ. Amen.",
    "easter+4": "O merciful and gracious God, you are the one who guides all on the path of truth by the light of your Word. Bring back those who have strayed from your truth. Give your grace to all who call on the name of Christ, to leave the evil and follow the good. Protect your children from this evil world by your Word and your Holy Spirit, and grant them eternal life in the name of our Lord Jesus Christ. Amen.",
    "easter+5": "Our kind and loving God, we thank you for hearing and answering our prayers. We pray to you in the name of our Lord Jesus Christ, trusting that you will grant us our requests as we ask in faith according to your will. Amen.",
    "ascension": "Almighty God, grant to all of us who believe in our ascended Savior Jesus Christ that we will live with him in heaven. Lord Jesus Christ, you who live and reign with the Father and the Holy Spirit, you defeated the power of death and sin and redeemed us, opening for us the door of heaven. Free us from sin and make us heirs of eternal life. Amen.",
    "ascension+1": "O Lord our God, we thank you for enlightening and comforting the hearts of believers with your Holy Spirit. Help us by your Spirit to think only of what is right and true. In the name of our Lord Jesus Christ, who lives and reigns with you and the Holy Spirit, one God forever and ever. Amen.",
    "pentecost": "Lord, our God, King of heaven and earth, we thank you for giving your only Son, our Lord Jesus Christ, to be our Savior. Holy Spirit, our God, we thank you for keeping us safe from the evil of this world and guiding us to walk in the path of holiness. Hear our prayers and accept our praise in the name of our Lord Jesus Christ. Amen.",
    "pentecost+1": "Our living and eternal God, we thank you for giving us your Holy Spirit to help and guide us in our life and ministry. We pray that in your holy church, built on the foundation of apostles and prophets, the gifts of the Holy Spirit may work according to your will, for your honor and for the edification of all believers. Inspire us to humble service, so that these gifts will not be a reason for us to boast, but a reason for all people to glory in the name of our Lord Jesus Christ. Amen.",
    "pentecost+2": "O Lord our God, Father of our Lord Jesus Christ, glory be to you! It is your will that all who believe in your Son, and are your children through holy baptism, be filled with the Holy Spirit. Lord, make us strong Christians, your sons and daughters, visible witnesses of the fruit of the Spirit in our lives. We pray in the name of our Lord Jesus Christ, who died and redeemed us with his blood, that you will always help us by the power of the Holy Spirit to grow towards your holiness and to put away the works of the flesh. Amen.",
    "trinity": "Almighty and eternal God, we, who are the work of your hands, thank you for giving us true faith so that we know you, our heavenly Father, your Son Jesus Christ, and the Holy Spirit. God, we pray that you comfort your church with this true faith and protect it from all harm and evil in the name of our Lord Jesus Christ. Amen.",
    "trinity+1": "O Lord our God, the protector of all who hope in you: in the name of our Lord Jesus Christ, in your great mercy protect us with your Holy Spirit so that we do not lose the gift of eternal life but remain faithful to your forever. Amen.",
    "trinity+2": "O Lord our God, without your help, we your children can do nothing good. Empower us by the hope we have in Christ Jesus your Son. We love you, because you are the one who called us and with your saving gospel. Help us by the power of your Holy Spirit to follow your will in our thoughts and actions. In the name of our Savior Jesus Christ. Amen.",
    "trinity+3": "Our God, who has called us to the fellowship of your Son, our Lord Jesus Christ, you are the one we trust. We thank you for sanctifying us with your Holy Spirit, and for making us your children through your holy sacraments. Lord, we pray in the name of Jesus Christ, the head of the church, to protect us and grant us unity in the one true faith. Amen.",
    "trinity+4": "Praise be to you, O Lord our God, for you alone are the creator of righteousness and the source of peace. In the name of our Lord Jesus Christ, we ask you to strengthen us with the power of your Holy Spirit so that we may live peaceful lives in this world, and that your church may resist the traps of the Devil and serve you truly. Amen.",
    "trinity+5": "Dear Lord our God, we thank you for the all the gifts you have prepared for those who love you. Pour the power of your love into our hearts so that we can love you more than anything else. Help us with your Holy Spirit so that we always treasure the hope that we have in your grace. In the name of our Lord Jesus Christ. Amen.",
    "trinity+6": "Almighty God, everything that is good comes from you. Strengthen our faith so that we do not waste the gift that you have given us. May your Holy Spirit always be with us. Help us to love your holy name with true love, for the sake of our Lord Jesus Christ. Amen.",
    "trinity+7": "Almighty God we praise you for bringing us out of the power of darkness into the light of your only Son Jesus Christ. As we travel through this dark world of sin on the way to our heavenly home, we ask you to enlighten us with the light of your Word and so enable us to see your glory in heaven. In the name of our Lord Jesus Christ who lives and reigns forever with you and the Holy Spirit. Amen.",
    "trinity+8": "Lord God our Heavenly Father, you are the one who called and entrusted your servants to serve you faithfully and wisely. You have promised your children that you will hear our prayers. Help us with your Holy Spirit so that we may ask only according to your will, and grant us what we ask for in the name of our Lord Jesus Christ. Amen.",
    "trinity+9": "O Lord our God, we honor you because you have forgiven our sins, and you daily protect us from evil. In this way, you show us that you are almighty God. May your Holy Spirit help us to be wise stewards who treasure the hope we have in you, and so fulfill the stewardship responsibility you have given us. Do not cut us off from the joy and grace of heaven. In the name of our Lord Jesus Christ. Amen.",
    "trinity+10": "Almighty and eternal God, your goodness is far greater than our thoughts, words, and deeds. Do not count our sins against us, but have mercy on us. O righteous God, grant us your true righteousness and give us wisdom to discern good from evil. Give us the spirit of prayer, and teach us to pray by your Holy Spirit, for we do not know how or what to ask for. In the name of your only Son, Jesus Christ our Lord. Amen.",
    "trinity+11": "O God our heavenly Father, may we ever listen to your living Word, given through our Lord Jesus Christ. We ask you in the name of Jesus to guide us by your Holy Spirit to speak only the truth before you and all people. Amen.",
    "trinity+12": "Almighty God, cause faith, hope and love to grow more and more in our hearts. Help us to obey what you command. In the name of our Lord Jesus Christ, give us your power in the Holy Spirit, so that we may find what you have promised. Amen.",
    "trinity+13": "Most High Lord our God, we give you high praise because you are our true King. Come into the midst of your church and receive our thanks for all the good things you do for us every day. Hear our prayers through our Lord Jesus Christ, who lives and reigns forever with you and the Holy Spirit. Amen.",
    "trinity+14": "O God, thank you for being the Creator and Protector of all, and for drawing us to yourself. Wake us up with your Holy Spirit to seek first your kingdom and your righteousness. We are ready to receive from your hand all that you give us in your grace. In the name of our Lord Jesus Christ. Amen.",
    "trinity+15": "God our Father, you are kind and merciful. All your works are beautiful and wonderful. We thank you for creating the earth and all the creatures in it, and for giving it to us. We pray in the name of your only-begotten Son, Jesus Christ, that you will fill us with your understanding so that we do not destroy creation with greed and carelessness and bring calamity to ourselves and the next generation, but instead help us fulfill our responsibility to protect and care for your beautiful and wonderful creation, according to your good and gracious will for us in Christ Jesus our Lord. Amen.",
    "trinity+16": "Almighty God our Creator, guide your people with your light so that we may walk on the right path all our days. Help us resist all evil with the power of your Holy Spirit, and give us your grace to serve you with a pure heart. In the name of our Lord Jesus Christ. Amen.",
    "trinity+17": "God, our heavenly Father, you know that we are a people who cannot keep your commandments. Therefore, in the name of our Lord Jesus Christ, we ask you to increase our love for following your law and hearing your Word. Guide our hearts with your Holy Spirit. Amen.",
    "trinity+18": "Our living and eternal God, you are the one who helps us with your Holy Spirit and enables us to pray. We ask you to hear our prayers and answer them according to your good and gracious will, in Jesus Christ our Lord. Amen.",
    "trinity+19": "O Lord our God, who created us in your image and likeness, we thank you for the land you have given and for all your blessings that come from it. We ask you in the name of our Lord Jesus Christ to help us work dilligently to use the gifts you have given us according to your will. Give your blessing to us, our family, our church, and our land, through Christ our Lord. Amen.",
    "trinity+20": "Dear God, heavenly Father, we thank you for giving forgiveness of sins to all who believe in your Son Jesus Christ. Give us the power to truly forgive all those who wrong us. Pour your love into our hearts so that we may walk in the way that is right for your children. In the name of our Lord Jesus Christ, who lives and reigns forever with you and the Holy Spirit. Amen.",
    "trinity+21": "Almighty God, you are the Changeless One who rules this world forever. While we live on this earth, help us by the power of the Holy Spirit to keep your law and walk in the path of the children of light, in the name of our Lord Jesus Christ. Amen.",
    "trinity+22": "O God our Father, your only Son, our Lord Jesus Christ, died and rose again and now reigns forever at your right hand. By your Holy Spirit, help us to cling to him as our only Savior, and so to receive eternal life with him forever in heaven. Amen.",
    "trinity+23": "Almighty God, Heavenly Father, we are sinners who deserve only wrath and judgment. But you saved us from eternal punishment by your only Son Jesus. Show us your kindness and increase your grace. In the name of our Lord Jesus Christ, your beloved Son, who lives and reigns forever with you and the Holy Spirit. Amen.",
    "judgment-1": "God, our heavenly Father, in your mercy protect us so that we do not fall asleep in sin like the foolish young women. Keep us watchful and alert by the power of the Holy Spirit. Help us to pray without ceasing, and at last enter your eternal kingdom. In the name of our Lord Jesus Christ. Amen.",
    "judgment": "Lord our God, while we live in this world, keep us ever mindful of the final judgment so that we live according to your will. Prepare our hearts by your Holy Spirit so that we may receive eternal life from you. In the name of our Lord Jesus Christ. Amen.",
    "circumcision": "O Lord God, who never changes, we thank you for giving your only Son to be our Savior. Help us by your Holy Spirit, in the name of our Lord Jesus Christ, so that we who are strangers and aliens in this world may follow him, and reach our home in the kingdom of heaven. Amen.",
    "temple": "Almighty and eternal God, on this day we remember that Mary, the mother of our Lord Jesus Christ, brought Jesus to the temple in obedience to the law. Prepare and help us with your Holy Spirit so that we too may come to your temple with a pure heart and stand before you without fear. In the name of our Lord Jesus Christ. Amen.",
    "annunciation": "O God, our heavenly Father, in your great kindness you revealed through your angel that your only Son would be born on this earth for us and for our salvation. Help us by your Holy Spirit to fulfill your will and always to give thanks for your kindness and mercy. In the name of your beloved Son Jesus Christ. Amen.",
    "tabor": "Almighty God our Father, we thank you for showing the glory of Christ to the disciples on the mountain. Help us by your Holy Spirit to walk through the darkness of this world remembering of the light of the glory of Christ, until we finally see his glory face to face. In the name of our Lord Jesus Christ. Amen.",
    "last": "Dear God our heavenly Father, you earnestly desire that no sinner be lost, but that all should repent and return to you. Do not judge us according to our sins, but look instead on our faith in Jesus. Strengthen us by the power of your Holy Spirit to fear, love, and serve you, in the name of our Lord Jesus Christ. Amen.",
    "newyear": "Lord God, we thank you for sending your chosen servant John the Baptist to prepare the way for your Son Jesus Christ by teaching and baptizing. Send your Holy Spirit to bring us to repentance, so that we leave the way of sin and follow our Lord Jesus Christ. For the sake of your holy name. Amen.",
    "mesqel": "O Lord Jesus Christ, you are our Lord and Savior, who willingly suffered and died on the cross for us sinners. You are the God who redeemed us from eternal death by dying on the cross and blotting out all our sins. As we celebrate this feast of your cross, sanctify us with your Holy Spirit. May we always live under your cross and keep your eyes fixed on you, so that we may walk according to your will. Hear our prayers for the sake of your holy name and glory. Amen.",
    "reformation": "O Lord our God, you are Lord of all nations on earth. We praise you for sending your servants to call and renew your church to its proper function. Now in our time, raise up among us preachers and teachers who are enlightened by your Spirit, whose voices will awaken your church and proclaim the reality of your kingdom. Keep them faithful to your Word and strengthened by it. Be their strong defender before their enemies. In the name of your Son, our Lord Jesus Christ, Amen.",
    "martyrs": "Almighty God, you have sent your servants to carry your message of love to people of all ages. We ask you to revive in us the memory of these servants of yours, whose faithful witness to the gospel led them to pass through the road of the cross. Give us your grace to follow them in their path of faith and devotion. Give us the courage to bear witness throughout our lives to the victory of your Son over sin and death. In the name of our Lord Jesus Christ. Amen."
  },
  "readings": [
    "Old Testament",
    "Epistle",
    "Gospel"
  ],
  "books": {
    "GEN": "Genesis",
    "EXO": "Exodus",
    "LEV": "Leviticus",
    "NUM": "Numbers",
    "DEU": "Deuteronomy",
    "JOS": "Joshua",
    "JDG": "Judges",
    "RUT": "Ruth",
    "1SA": "1 Samuel",
    "2SA": "2 Samuel",
    "1KI": "1 Kings",
    "2KI": "2 Kings",
    "1CH": "1 Chronicles",
    "2CH": "2 Chronicles",
    "EZR": "Ezra",
    "NEH": "Nehemiah",
    "EST": "Esther",
    "JOB": "Job",
    "PSA": "Psalms",
    "PRO": "Proverbs",
    "ECC": "Ecclesiastes",
    "SNG": "Song of Solomon",
    "ISA": "Isaiah",
    "JER": "Jeremiah",
    "LAM": "Lamentations",
    "EZK": "Ezekiel",
    "DAN": "Daniel",
    "HOS": "Hosea",
    "JOL": "Joel",
    "AMO": "Amos",
    "OBA": "Obadiah",
    "JON": "Jonah",
    "MIC": "Micah",
    "NAM": "Nahum",
    "HAB": "Habakkuk",
    "ZEP": "Zephaniah",
    "HAG": "Haggai",
    "ZEC": "Zechariah",
    "MAL": "Malachi",
    "MAT": "Matthew",
    "MRK": "Mark",
    "LUK": "Luke",
    "JHN": "John",
    "ACT": "Acts",
    "ROM": "Romans",
    "1CO": "1 Corinthians",
    "2CO": "2 Corinthians",
    "GAL": "Galatians",
    "EPH": "Ephesians",
    "PHP": "Philippians",
    "COL": "Colossians",
    "1TH": "1 Thessalonians",
    "2TH": "2 Thessalonians",
    "1TI": "1 Timothy",
    "2TI": "2 Timothy",
    "TIT": "Titus",
    "PHM": "Philemon",
    "HEB": "Hebrews",
    "JAS": "James",
    "1PE": "1 Peter",
    "2PE": "2 Peter",
    "1JN": "1 John",
    "2JN": "2 John",
    "3JN": "3 John",
    "JUD": "Jude",
    "REV": "Revelation"
  },
  "books_abbr": {
    "GEN": "Gen.",
    "EXO": "Ex.",
    "LEV": "Lev.",
    "NUM": "Num.",
    "DEU": "Deut.",
    "JOS": "Josh.",
    "JDG": "Judg.",
    "RUT": "Ruth",
    "1SA": "1Sam.",
    "2SA": "2Sam.",
    "1KI": "1Kings",
    "2KI": "2Kings",
    "1CH": "1Chron.",
    "2CH": "2Chron.",
    "EZR": "Ezra",
    "NEH": "Neh.",
    "EST": "Est.",
    "JOB": "Job",
    "PSA": "Ps.",
    "PRO": "Prov.",
    "ECC": "Eccles.",
    "SNG": "Song",
    "ISA": "Isa.",
    "JER": "Jer.",
    "LAM": "Lam.",
    "EZK": "Ezek.",
    "DAN": "Dan.",
    "HOS": "Hos.",
    "JOL": "Joel",
    "AMO": "Amos",
    "OBA": "Obad.",
    "JON": "Jonah",
    "MIC": "Mic.",
    "NAM": "Nah.",
    "HAB": "Hab.",
    "ZEP": "Zeph.",
    "HAG": "Hag.",
    "ZEC": "Zech.",
    "MAL": "Mal.",
    "MAT": "Matt.",
    "MRK": "Mark",
    "LUK": "Luke",
    "JHN": "John",
    "ACT": "Acts",
    "ROM": "Rom.",
    "1CO": "1Cor.",
    "2CO": "2Cor.",
    "GAL": "Gal.",
    "EPH": "Eph.",
    "PHP": "Phil.",
    "COL": "Col.",
    "1TH": "1Thess.",
    "2TH": "2Thess.",
    "1TI": "1Tim.",
    "2TI": "2Tim.",
    "TIT": "Titus",
    "PHM": "Philem.",
    "HEB": "Heb.",
    "JAS": "James",
    "1PE": "1Pet.",
    "2PE": "2Pet.",
    "1JN": "1John",
    "2JN": "2John",
    "3JN": "3John",
    "JUD": "Jude",
    "REV": "Rev."
  },
  "typography": {
    "chapter_verse": ":",
    "verse_span": "-",
    "verse_list": ",",
    "chapter_list": ";",
    "chapter_span": "–"
  }
}